botmaro_secrets_manager-0.3.0.dist-info/licenses/LICENSE
secrets_manager/__init__.py
secrets_manager/cli.py
secrets_manager/config.py
secrets_manager/core.py
secrets_manager/formatters.py
secrets_manager/gsm.py
secrets_manager/validator.py
botmaro_secrets_manager-0.3.0.dist-info/METADATA
botmaro_secrets_manager-0.3.0.dist-info/WHEEL
botmaro_secrets_manager-0.3.0.dist-info/entry_points.txt
botmaro_secrets_manager-0.3.0.dist-info/top_level.txt
botmaro_secrets_manager-0.3.0.dist-info/RECORD
