Metadata-Version: 2.4
Name: botmaro-secrets-manager
Version: 0.3.0
Summary: A standalone secret management tool for multi-environment deployments with Google Secret Manager
Author: Botmaro Team
License: MIT
Project-URL: Homepage, https://github.com/B9ice/botmaro-gcp-secret-manager
Project-URL: Repository, https://github.com/B9ice/botmaro-gcp-secret-manager
Project-URL: Issues, https://github.com/B9ice/botmaro-gcp-secret-manager/issues
Keywords: secrets,gsm,google-secret-manager,environment,deployment
Classifier: Development Status :: 4 - Beta
Classifier: Intended Audience :: Developers
Classifier: License :: OSI Approved :: MIT License
Classifier: Programming Language :: Python :: 3
Classifier: Programming Language :: Python :: 3.8
Classifier: Programming Language :: Python :: 3.9
Classifier: Programming Language :: Python :: 3.10
Classifier: Programming Language :: Python :: 3.11
Requires-Python: >=3.8
License-File: LICENSE
Requires-Dist: google-cloud-secret-manager>=2.16.0
Requires-Dist: typer[all]>=0.9.0
Requires-Dist: pyyaml>=6.0
Requires-Dist: pydantic>=2.0.0
Requires-Dist: python-dotenv>=1.0.0
Requires-Dist: rich>=13.0.0
Provides-Extra: dev
Requires-Dist: pytest>=7.0.0; extra == "dev"
Requires-Dist: black>=23.0.0; extra == "dev"
Requires-Dist: mypy>=1.0.0; extra == "dev"
Requires-Dist: types-PyYAML>=6.0.0; extra == "dev"
Dynamic: license-file
